emcore-0.0.5.data/data/bin/em-image
emcore-0.0.5.data/data/bin/em-test
emcore-0.0.5.data/data/bin/em-table
emcore.libs/libpng12-640ca796.so.0.49.0
emcore.libs/libemcore-eab94bff.so
emcore.libs/libfftw3-3a26e910.so.3.2.3
emcore.libs/libz-eb09ad1d.so.1.2.3
emcore.libs/libtiff-e6ae6939.so.3.9.4
emcore.libs/libjpeg-7feae879.so.62.0.0
emcore.libs/libfftw3f-19f177d3.so.3.2.3
emcore.libs/libsqlite3-bed55523.so.0.8.6
emcore/__init__.py
emcore/_emcore.so
emcore/tests/__init__.py
emcore/tests/test_base.py
emcore/tests/test_type.py
emcore/tests/matplotlib_volume.py
emcore/tests/numpy_stats.py
emcore/tests/__main__.py
emcore/tests/test_object.py
emcore/tests/test_image.py
emcore/tests/test_table.py
emcore/tests/matplotlib_image.py
emcore/tests/base.py
emcore-0.0.5.dist-info/top_level.txt
emcore-0.0.5.dist-info/WHEEL
emcore-0.0.5.dist-info/METADATA
emcore-0.0.5.dist-info/RECORD
